{
  "applications": "*",
  "changelogDate": "20230707111342",
  "clientRootFolder": "settings",
  "databaseType": "sql",
  "dto": "mapstruct",
  "embedded": false,
  "entityTableName": "t_functionality_endpoint_mapping",
  "fields": [
    {
      "fieldName": "functionalityEndpointMappingId",
      "fieldType": "Long",
      "options": {
        "id": true
      }
    },
    {
      "fieldName": "endpointId",
      "fieldType": "Long"
    },
    {
      "fieldName": "functionalityId",
      "fieldType": "Long"
    },
    {
      "fieldName": "mappingDesc",
      "fieldType": "String"
    },
    {
      "fieldName": "status",
      "fieldType": "String"
    },
    {
      "fieldName": "createdById",
      "fieldType": "Long"
    },
    {
      "fieldName": "createdByName",
      "fieldType": "String"
    },
    {
      "fieldName": "createdDate",
      "fieldType": "LocalDate"
    },
    {
      "fieldName": "updatedById",
      "fieldType": "Long"
    },
    {
      "fieldName": "updatedByName",
      "fieldType": "String"
    },
    {
      "fieldName": "updatedDate",
      "fieldType": "LocalDate"
    },
    {
      "fieldName": "functionalityEndpointMappingUuid",
      "fieldType": "UUID"
    }
  ],
  "fluentMethods": true,
  "jpaMetamodelFiltering": false,
  "microserviceName": "settings",
  "name": "FunctionalityEndpointMapping",
  "pagination": "pagination",
  "readOnly": false,
  "relationships": [],
  "service": "serviceImpl",
  "skipCheckLengthOfIdentifier": true
}
